error_explorer/__init__.py
error_explorer/breadcrumbs.py
error_explorer/cli.py
error_explorer/client.py
error_explorer/quick_test.py
error_explorer/test_enhanced_sdk.py
error_explorer/types.py
error_explorer/integrations/__init__.py
error_explorer/integrations/django.py
error_explorer/integrations/fastapi.py
error_explorer/integrations/flask.py
error_explorer/services/__init__.py
error_explorer/services/offline_manager.py
error_explorer/services/quota_manager.py
error_explorer/services/rate_limiter.py
error_explorer/services/retry_manager.py
error_explorer/services/sdk_monitor.py
error_explorer/services/security_validator.py
error_explorer_python-1.0.0.dist-info/licenses/LICENSE
error_explorer_python-1.0.0.dist-info/METADATA
error_explorer_python-1.0.0.dist-info/WHEEL
error_explorer_python-1.0.0.dist-info/entry_points.txt
error_explorer_python-1.0.0.dist-info/top_level.txt
error_explorer_python-1.0.0.dist-info/RECORD
