Metadata-Version: 2.4
Name: error-explorer-python
Version: 1.0.0
Summary: Python SDK for Error Explorer - Capture and report errors automatically
Home-page: https://github.com/Manguet/ErrorReportPythonSDK
Author: Manguet
Author-email: benjamin.manguet@gmail.com
Project-URL: Bug Tracker, https://github.com/Manguet/ErrorReportPythonSDK/issues
Project-URL: Source, https://github.com/Manguet/ErrorReportPythonSDK
Keywords: error monitoring debugging logging django flask fastapi python
Classifier: Development Status :: 5 - Production/Stable
Classifier: Intended Audience :: Developers
Classifier: License :: OSI Approved :: MIT License
Classifier: Operating System :: OS Independent
Classifier: Programming Language :: Python :: 3
Classifier: Programming Language :: Python :: 3.7
Classifier: Programming Language :: Python :: 3.8
Classifier: Programming Language :: Python :: 3.9
Classifier: Programming Language :: Python :: 3.10
Classifier: Programming Language :: Python :: 3.11
Classifier: Programming Language :: Python :: 3.12
Classifier: Topic :: Software Development :: Debuggers
Classifier: Topic :: Software Development :: Quality Assurance
Classifier: Topic :: System :: Logging
Classifier: Topic :: System :: Monitoring
Requires-Python: >=3.7
License-File: LICENSE
Requires-Dist: requests>=2.25.0
Provides-Extra: django
Requires-Dist: Django>=3.0; extra == "django"
Provides-Extra: flask
Requires-Dist: Flask>=1.0; extra == "flask"
Provides-Extra: fastapi
Requires-Dist: FastAPI>=0.65.0; extra == "fastapi"
Provides-Extra: dev
Requires-Dist: pytest>=6.0; extra == "dev"
Requires-Dist: pytest-cov>=2.10; extra == "dev"
Requires-Dist: black>=21.0; extra == "dev"
Requires-Dist: isort>=5.0; extra == "dev"
Requires-Dist: flake8>=3.8; extra == "dev"
Requires-Dist: mypy>=0.800; extra == "dev"
Dynamic: author
Dynamic: author-email
Dynamic: classifier
Dynamic: description
Dynamic: description-content-type
Dynamic: home-page
Dynamic: keywords
Dynamic: license-file
Dynamic: project-url
Dynamic: provides-extra
Dynamic: requires-dist
Dynamic: requires-python
Dynamic: summary
